pyqt_timer_label/__init__.py
pyqt_timer_label/timerLabel.py
pyqt_timer_label-0.0.1.dist-info/LICENSE
pyqt_timer_label-0.0.1.dist-info/METADATA
pyqt_timer_label-0.0.1.dist-info/WHEEL
pyqt_timer_label-0.0.1.dist-info/top_level.txt
pyqt_timer_label-0.0.1.dist-info/RECORD
