Metadata-Version: 2.1
Name: pyqt-timer-label
Version: 0.0.1
Summary: PyQt QLabel adapted to timer feature
Home-page: https://github.com/yjg30737/pyqt-timer-label.git
Author: Jung Gyu Yoon
Author-email: yjg30737@gmail.com
License: MIT
Platform: UNKNOWN
License-File: LICENSE
Requires-Dist: PyQt5 (>=5.8)
Requires-Dist: pyqt-responsive-label (>=0.0.1)
